airzone/__init__.py
airzone/aido.py
airzone/innobus.py
airzone/localapi.py
airzone/protocol.py
airzone/utils.py
python_airzone-1.data/scripts/airzone_cli.py
tests/__init__.py
tests/test_localapi.py
python_airzone-1.dist-info/LICENSE
python_airzone-1.dist-info/METADATA
python_airzone-1.dist-info/WHEEL
python_airzone-1.dist-info/top_level.txt
python_airzone-1.dist-info/RECORD
