Metadata-Version: 2.1
Name: python-airzone
Version: 1
Summary: 'Python library for interfacing with Airzone using the modbus protocol',  # Required
Home-page: https://github.com/gpulido/python-airzone
Author: Gabriel Pulido
Author-email: gabriel.pulidodetorres@gmail.com
License: MIT
Keywords: innobus,airzone,modbus,HVAC
Platform: UNKNOWN
Classifier: Development Status :: 3 - Alpha
Classifier: Intended Audience :: Developers
Classifier: Topic :: Software Development :: Build Tools
Classifier: License :: OSI Approved :: MIT License
Classifier: Programming Language :: Python :: 3
Classifier: Programming Language :: Python :: 3.4
Classifier: Programming Language :: Python :: 3.5
Classifier: Programming Language :: Python :: 3.6
Classifier: Programming Language :: Python :: 3.7
Classifier: Programming Language :: Python :: 3.8
Classifier: Programming Language :: Python :: 3.9
License-File: LICENSE
Requires-Dist: pyModbus
Requires-Dist: pybase64
Requires-Dist: importlib-metadata
Requires-Dist: requests
Requires-Dist: Python-Deprecated
